confluent_kafka/__init__.py
confluent_kafka/cimpl.cpython-311-x86_64-linux-gnu.so
confluent_kafka/deserializing_consumer.py
confluent_kafka/error.py
confluent_kafka/serializing_producer.py
confluent_kafka/_model/__init__.py
confluent_kafka/_util/__init__.py
confluent_kafka/_util/conversion_util.py
confluent_kafka/_util/validation_util.py
confluent_kafka/admin/__init__.py
confluent_kafka/admin/_acl.py
confluent_kafka/admin/_cluster.py
confluent_kafka/admin/_config.py
confluent_kafka/admin/_group.py
confluent_kafka/admin/_listoffsets.py
confluent_kafka/admin/_metadata.py
confluent_kafka/admin/_resource.py
confluent_kafka/admin/_scram.py
confluent_kafka/admin/_topic.py
confluent_kafka/avro/__init__.py
confluent_kafka/avro/cached_schema_registry_client.py
confluent_kafka/avro/error.py
confluent_kafka/avro/load.py
confluent_kafka/avro/serializer/__init__.py
confluent_kafka/avro/serializer/message_serializer.py
confluent_kafka/kafkatest/__init__.py
confluent_kafka/kafkatest/verifiable_client.py
confluent_kafka/kafkatest/verifiable_consumer.py
confluent_kafka/kafkatest/verifiable_producer.py
confluent_kafka/schema_registry/__init__.py
confluent_kafka/schema_registry/avro.py
confluent_kafka/schema_registry/error.py
confluent_kafka/schema_registry/json_schema.py
confluent_kafka/schema_registry/protobuf.py
confluent_kafka/schema_registry/schema_registry_client.py
confluent_kafka/serialization/__init__.py
confluent_kafka/src/Admin.c
confluent_kafka/src/AdminTypes.c
confluent_kafka/src/Consumer.c
confluent_kafka/src/Metadata.c
confluent_kafka/src/Producer.c
confluent_kafka/src/confluent_kafka.c
confluent_kafka/src/confluent_kafka.h
superstream_confluent_kafka_beta-2.5.1.data/data/LICENSE.txt
superstream_confluent_kafka_beta-2.5.1.dist-info/LICENSE.txt
superstream_confluent_kafka_beta-2.5.1.dist-info/METADATA
superstream_confluent_kafka_beta-2.5.1.dist-info/WHEEL
superstream_confluent_kafka_beta-2.5.1.dist-info/top_level.txt
superstream_confluent_kafka_beta-2.5.1.dist-info/RECORD
